{"cnt_4b44a4d544ee7":"visual form recognition","cnt_4b44a5321112e":"response inhibition","cnt_4b4a2f46e2faa":"response inhibition","cnt_4b4a538defadc":"attentional focusing","cnt_4b4a5473705db":"working memory","cnt_4b4a5481dc0f2":"working memory","cnt_4b4a5490f1bb4":"working memory","cnt_4b4a54dd8d597":"working memory","cnt_4b4a5f85437c2":"working memory","cnt_4b4a609f11b96":"working memory","cnt_4b7c0325a9f17":"central coherence","cnt_4b7c03351fc78":"central coherence","cnt_4b7c101e9b549":"task switching","cnt_4b7c108cc7a68":"working memory","cnt_4b7c10b1b1de1":"set shifting","cnt_4b82d26b480ea":"central coherence","cnt_4b8436c051c94":"interference","cnt_4bd1ec505dd14":"attention shifting","cnt_4be6ec4cb064c":"lexical access","cnt_4be6ec6e29f57":"memory retrieval","cnt_4c6b5fd5bfc41":"oddball detection","cnt_4c9975fc3078c":"visual working memory","cnt_4cacee8ad4b14":"potential monetary loss","cnt_4cacf26718047":"visual form recognition","cnt_4d949c8f3101c":"phonological working memory","cnt_4d949c9b01604":"phonological working memory","cnt_4de56f49c2858":"phonological working memory","cnt_4de56f7a17762":"working memory","cnt_4de57f6d43cfd":"cognitive control","cnt_4de583fcb0789":"face recognition","cnt_4de584598a9c7":"face recognition","cnt_4de6716415d2d":"visual perception","cnt_4de671af5aeb3":"form perception","cnt_4de671d131ff9":"form perception","cnt_4de671e75974e":"form perception","cnt_4de6722368730":"form perception","cnt_4de674d6a85e6":"visual perception","cnt_4de6758abdfa5":"implicit memory","cnt_4de677aa1e1bb":"form perception","cnt_4de67800c904a":"form perception","cnt_4de678e027440":"visual object recognition","cnt_4de6875390f37":"visual working memory","cnt_4de68ca153c38":"lexical retrieval","cnt_4de6a278a7dd5":"chunking","cnt_4de6a2be90526":"memory retrieval","cnt_4de6a2f38a5ed":"chunking","cnt_4de6a334313b1":"memory retrieval","cnt_4de6ad74bd885":"face recognition","cnt_4de6add395167":"face recognition","cnt_4de6ae3e231dd":"face recognition","cnt_4de6b5d032f89":"risk seeking","cnt_4de6b69d1e765":"reward processing","cnt_4de6b87a44743":"semantic knowledge","cnt_4de6bfac7a994":"response selection","cnt_4de6bfdf5905a":"response inhibition","cnt_4de6c00e51eda":"decision","cnt_4de6c02033259":"decision","cnt_4de6c3c82d46d":"inhibition of return","cnt_4de6c5f53e708":"risk seeking","cnt_4de6c84f74508":"pavlovian conditioning","cnt_4de6c945846f2":"pavlovian conditioning","cnt_4de6c9842dbbe":"association learning","cnt_4de6d03ae67ac":"syntactic parsing","cnt_4de6d0d5790a3":"syntactic parsing","cnt_4de6d1194349d":"language comprehension","cnt_4de6d1650c739":"linguistic competence","cnt_4de6d2747197f":"linguistic competence","cnt_4de6d42855dcd":"language comprehension","cnt_4de6d45dd9ceb":"syntactic parsing","cnt_4de7b92a0ce43":"color perception","cnt_4de7c5b19456f":"false memory","cnt_4de7c5df194ea":"forgetting","cnt_4de7c6ae5a2a1":"word recognition","cnt_4de7d07b4366d":"word recognition","cnt_4de7d0b31ce2e":"forgetting","cnt_4de7d854ceb50":"risk seeking","cnt_4de7d90024fe4":"reward processing","cnt_4de7d90ca34da":"risk","cnt_4de7dc695fabb":"deception","cnt_4de7ddfb129a6":"theory of mind","cnt_4de7de54cdce7":"theory of mind","cnt_4de7e52cd0ad6":"convergent thinking","cnt_4de7e54b3b8d8":"logic","cnt_4de90fe2177d0":"active maintenance","cnt_4de919cf2b2bd":"memory retrieval","cnt_4de91ce5f279a":"risk seeking","cnt_4de929a613652":"working memory","cnt_4de929f98367a":"active retrieval","cnt_4de92b983089e":"motor control","cnt_4de93a6779688":"auditory attention","cnt_4de93d2864ae9":"short term memory","cnt_4de93ddadf379":"short term memory","cnt_4de93e2a13bb5":"short term memory","cnt_4de93e831c09d":"short term memory","cnt_4de948beb7f3c":"motor control","cnt_4de95f0aa8476":"cognitive control","cnt_4de963f853b03":"motor control","cnt_4de968d88e3d3":"acoustic encoding","cnt_4de96cd8c9aad":"episodic memory","cnt_4decfedb91973":"response selection","cnt_4ded050f2e7f1":"pattern recognition","cnt_4ded127195273":"emotion perception","cnt_4ded129f8c996":"face recognition","cnt_4ded2a911252c":"motor control","cnt_4ded2aa1ea79d":"motor control","cnt_4ded3a95a6098":"attention span","cnt_4ded3b16cdb74":"gaze","cnt_4ded480d5aec0":"phonological working memory","cnt_4ded4b345f82a":"emotional memory","cnt_4ded4b7c49083":"chunking","cnt_4ded4dc5b5118":"behavioral inhibition (cognitive)","cnt_4ded518b33a0b":"motor planning","cnt_4ded51930eba6":"motor control","cnt_4ded542c8c4f8":"reading","cnt_4ded60eb3a50f":"central coherence","cnt_4dee50b24d8c4":"imageability","cnt_4dee50d11696f":"motor planning","cnt_4dee50e19a0a5":"cognitive effort","cnt_4dee551d3a46b":"mental representation","cnt_4dee593ebfcc7":"cognitive development","cnt_4dee5f41244cc":"working memory","cnt_4dee7fcd869e8":"inductive reasoning","cnt_4deeb0951bd72":"emotion perception","cnt_4deff762a9fb7":"pattern recognition","cnt_4df108c45e041":"attention shifting","cnt_4df10d2fb170f":"risk seeking","cnt_4df10f9cbd86c":"color perception","cnt_4df118fd720dd":"motor control","cnt_4df133a20d8da":"perceptual binding","cnt_4df133b48842d":"spatial ability","cnt_4df13aaa3f2be":"working memory","cnt_4df13d6084e80":"language processing","cnt_4df1456d05cab":"language learning","cnt_4df1585e55f60":"auditory working memory","cnt_4df24f7376278":"acoustic processing","cnt_4df25f35f17e3":"conventionality","cnt_4df26493887a0":"spatial ability","cnt_4df265ff04368":"mental rotation","cnt_4df26816e1c98":"attentional focusing","cnt_4df28c7e2f855":"cognitive control","cnt_4df2917218780":"procedural memory","cnt_4df2918824fb9":"procedural memory","cnt_4df298fddce13":"articulatory planning","cnt_4df29978d4002":"articulatory planning","cnt_4df29e99a47ae":"object manipulation","cnt_4df2a27d637b3":"somatosensation","cnt_4df2a4cb64388":"thermosensation","cnt_4df2a4d2ecac9":"somatosensation","cnt_4df2a4de25215":"thermosensation","cnt_4df663cf4ea8a":"object perception","cnt_4df66400663ec":"object perception","cnt_4df67df7aaaea":"olfactory perception","cnt_4df6818a8bcec":"attentional focusing","cnt_4df685e797da2":"form perception","cnt_4df689e663ffe":"somatosensation","cnt_4df689fe846de":"somatosensation","cnt_4df68cac967cc":"semantic working memory","cnt_4df6974d8c674":"motor control","cnt_4df69a929ce35":"audition","cnt_4df69c712873f":"visual perception","cnt_4df6a3169f42a":"acoustic phonetic processing","cnt_4df6a77053b3f":"object recognition","cnt_4df7af3c32a49":"acoustic phonetic processing","cnt_4df7bfc72c237":"motor planning","cnt_4df8e29765d7b":"attention shifting","cnt_4df8e2af408ed":"attentional focusing","cnt_4df8ef730f4cb":"","cnt_4df8ef7a8d7c3":"risk seeking","cnt_4df8fc0a76f53":"morphological processing","cnt_4df8fc1e54759":"lexical processing","cnt_4df9011fa1f5b":"semantic memory","cnt_4df9015bcfad3":"semantic memory","cnt_4df914f00dd42":"phonological encoding","cnt_4df91d85ed597":"visual attention","cnt_4df91dc172a88":"divided attention","cnt_4df91dd29b1c6":"visual attention","cnt_4df928c85f523":"visuospatial sketch pad","cnt_4df92bccc5ae1":"working memory retrieval","cnt_4df938dc89175":"analogical reasoning","cnt_4df93a3c9bd2c":"instrumental learning","cnt_4dfa3bb649f8a":"risk seeking","cnt_4dfa3e4d70781":"auditory working memory","cnt_4dfa3ebab2930":"sentence comprehension","cnt_4dfa3ef2bcbf0":"divided attention","cnt_4dfa3f0edd3d4":"divided attention","cnt_4dfa42ba0f7c2":"set shifting","cnt_4dfa42dddd062":"judgment","cnt_4dfa46d8c1622":"divided attention","cnt_4dfa4752a1120":"divided attention","cnt_4dfa523d45d5b":"cognitive load","cnt_4dfa6bad0c724":"sentence comprehension","cnt_4dfa6be222aa7":"phonological working memory","cnt_4dfa704eaedf9":"spreading activation","cnt_4dfa709c313b1":"semantic processing","cnt_4dfa7d117d48f":"motor learning","cnt_4dfa7d1ad09a6":"procedural memory","cnt_4dfa8214869b9":"task switching","cnt_4dfa838286e12":"","cnt_4dfa90af8345d":"motor control","cnt_4dfa93ee97bc8":"source memory","cnt_4dfa94d49dc90":"source memory","cnt_4dfb9a322c52f":"spatial ability","cnt_4dfb9b0719363":"spatial working memory","cnt_4dfbaef575808":"working memory retrieval","cnt_4dfbaf2722de5":"maintenance","cnt_4dfbaf4e94f96":"serial search","cnt_4dfbb1f51259f":"response inhibition","cnt_4dfbcad0d0f28":"mood","cnt_4dfbd05eb07d6":"emotion perception","cnt_4dfbd9e47c418":"mood","cnt_4dfbe08944a96":"syntactic parsing","cnt_4dff7fcf1b8a2":"syntactic parsing","cnt_4dff80aec63b6":"text comprehension","cnt_4dff8603c1398":"inhibition of return","cnt_4dff865de2859":"","cnt_4dff9a6e99c08":"language comprehension","cnt_4dffaa78530b6":"theory of mind","cnt_4dffb78e1edc6":"acoustic phonetic processing","cnt_4dffb9c632156":"visual search","cnt_4dffd3273f13e":"chunking","cnt_4dffd4ed38b03":"visual search","cnt_4dffdeb36edc5":"spatial ability","cnt_4dffded7a9be2":"mental rotation","cnt_4dffdf0929a7b":"spatial ability","cnt_4e00ccaa100fd":"","cnt_4e00e397017e2":"spatial ability","cnt_4e00fd3de3b0a":"visual working memory","cnt_4e00fd62beac3":"visual attention","cnt_4e00ffaa486fa":"visual search","cnt_4e0101e7e8898":"visual attention","cnt_4e0104d85693b":"visual search","cnt_4e010b32b9f74":"","cnt_4e011a8762e55":"logical reasoning","cnt_4e011aded6b9e":"spatial ability","cnt_4e011afe30540":"semantic knowledge","cnt_4e011b28cebdc":"verbal fluency","cnt_4e011cb5c3e85":"cognitive development","cnt_4e0125dc5bc09":"semantic knowledge","cnt_4e01263d51c93":"verbal fluency","cnt_4e012662da2d7":"mental arithmetic","cnt_4e01268a18f79":"semantic knowledge","cnt_4e0126b9ec56b":"semantic knowledge","cnt_4e0126dc131ec":"semantic knowledge","cnt_4e012702f0951":"logical reasoning","cnt_4e012722eeb57":"crystallized intelligence","cnt_4e0129bf96513":"cognitive development","cnt_4e012e2269d7d":"verbal memory","cnt_4e012fc0a6d05":"verbal memory","cnt_4e01306ba8db6":"visuospatial sketch pad","cnt_4e013090c4cf1":"visuospatial sketch pad","cnt_4e0130c979bf1":"auditory memory","cnt_4e0133e4d4fe1":"retention","cnt_4e0182336c9cc":"response execution","cnt_4e0219a2de6be":"spatial ability","cnt_4e022a9861397":"phonological encoding","cnt_4e022d7430161":"semantic processing","cnt_4e02368e6d840":"iconic memory","cnt_4e023794e822b":"working memory","cnt_4e0237ba58871":"lexical access","cnt_4e023c2ae3c76":"preattentive processing","cnt_4e02433a9f223":"lexical access","cnt_4e0243468cb6f":"verbal fluency","cnt_4e0253808fe82":"lexical access","cnt_4e025467f28e7":"verbal fluency","cnt_4e025694022e0":"semantic processing","cnt_4e02569dd0139":"semantic knowledge","cnt_4e025d79cc9f9":"motor control","cnt_4e025d8d96ecf":"sublexical route","cnt_4e02624559a17":"articulatory rehearsal","cnt_4e026543eae67":"active maintenance","cnt_4e02654a92111":"speech production","cnt_4e026dfa02b6d":"happiness","cnt_4e027155c037c":"mood","cnt_4e037a9a47d41":"spatial ability","cnt_4e038151ee9fb":"pain","cnt_4e0381ab6d190":"excitation","cnt_4e038ad0147d7":"selective attention","cnt_4e038b1c6fd1f":"serial search","cnt_4e038ba42d3a7":"conjunction search","cnt_4e03951a4914c":"perceptual learning","cnt_4e039557ad404":"reading","cnt_4e0399bbae0ed":"motor control","cnt_4e03ae76b40ab":"motor control","cnt_4e03b364135e2":"conditional reasoning","cnt_4e03b6ae397cc":"semantic knowledge","cnt_4e03b8b959bc9":"semantic knowledge","cnt_4e03b8c2457b4":"verbal fluency","cnt_4e03bc67764f5":"risk seeking","cnt_4e03bc8177610":"risk seeking","cnt_4e08ed0d8815f":"creative cognition","cnt_4e08ed6a4d30d":"sentence comprehension","cnt_4e08edac14ee7":"response inhibition","cnt_4e08f5aa73703":"phonological working memory","cnt_4e08fb9717d43":"chunking","cnt_4e08fdee5aec9":"procedural memory","cnt_4e08fe051b67b":"semantic working memory","cnt_4e08fe37729fc":"motor control","cnt_4e08fefbf0382":"procedural memory","cnt_4e41708078f47":"conflict detection","cnt_4e496d6e12225":"cognitive control","cnt_4e5d087f98fb2":"pain","cnt_4e611331826a0":"pain","cnt_4ebca1f15eb7d":"selective control","cnt_4ebca202935c6":"response selection","cnt_4ebca22149619":"response selection","cnt_4ebca72d737c1":"visual form recognition","cnt_4ebca9e1d3a16":"auditory tone discrimination","cnt_4ebcaa463d20e":"response selection","cnt_4ebcaa52e7dbd":"numerical comparison","cnt_4ebcaa755a7e5":"visual form recognition","cnt_4ebcaad4c41d7":"categorization","cnt_4f41830a3d5a9":"episodic memory","cnt_4fb3f6ec53aa5":"Gestalt grouping","cnt_4ffcb50c3f71c":"attentional blink","cnt_4ffdbab8b5539":"auditory perception","cnt_50046d4f1c8a1":"set shifting","cnt_500478a733748":"autobiographical memory","cnt_50049a0f821aa":"cueing","cnt_5005b3ba37b11":"visual search","cnt_5005c1421ee49":"attention","cnt_5005c2c544201":"visual search","cnt_5005ca466073a":"decision making","cnt_5005cae1dffba":"proprioception","cnt_5005cc79902cc":"autonoesis","cnt_5007088618bd2":"attention","cnt_50070d3b312f4":"impulsivity","cnt_50070f2604b71":"impulsivity","cnt_50070f5d10c03":"attention","cnt_50070f9310204":"attention","cnt_500712871f6d5":"spatial working memory","cnt_5007128e8defa":"spatial working memory","cnt_50071af2372d9":"attention","cnt_5007217a45778":"context memory","cnt_500723252de72":"automaticity","cnt_5007421b7d846":"motor control","cnt_5007422433506":"motor control","cnt_500742e46e628":"motor control","cnt_5007432c64f97":"motor control","cnt_500daccbafe09":"encoding","cnt_500ddba625847":"spatial memory","cnt_500ed6d06dd2e":"inhibition","cnt_500edcfd883ea":"language processing","cnt_5016e1b12e5c8":"cognitive control","cnt_5016e59e25341":"behavioral inhibition (cognitive)","cnt_5016e5ab53cce":"behavioral inhibition (cognitive)","cnt_5016e5b8068a9":"behavioral inhibition (cognitive)","cnt_5016e5c349611":"behavioral inhibition (cognitive)","cnt_5016e5cec4bf4":"behavioral inhibition (cognitive)","cnt_501702188843e":"figure ground segregation","cnt_501715cead551":"spatial memory","cnt_50184d223ef01":"planning","cnt_50185135a51fc":"impulsivity","cnt_50185b18ad99e":"inattention","cnt_50185b2433de1":"impulsivity","cnt_50200ddfae9f9":"semantic memory","cnt_5020196a49a19":"verbal memory","cnt_5020421e4a79e":"pavlovian conditioning","cnt_5020507780603":"working memory","cnt_50215d225f015":"impulsivity","cnt_502168c10e933":"domain specificity","cnt_502174397e768":"resistance to distractor inference","cnt_5021877eb2bcf":"global precedence","cnt_502199a142cab":"language comprehension","cnt_5021a042336c1":"decision making","cnt_5021ae2c2ab3c":"logical reasoning","cnt_5021b4664cfbb":"language comprehension","cnt_5021b53e64523":"language acquisition","cnt_5021b5773a9ae":"language acquisition","cnt_5022b4da18b61":"language acquisition","cnt_5022b5173b371":"language comprehension","cnt_5022b5727f9d6":"language acquisition","cnt_5022b85961b86":"impulsivity","cnt_5022e4acafe58":"emotion","cnt_5022e4e75d375":"attentional focusing","cnt_5022eb6a0eabd":"attentional focusing","cnt_5022ec302de82":"emotion","cnt_5022f0d06e757":"anxiety","cnt_5022f1079e925":"emotion","cnt_5023f9f966183":"association learning","cnt_5023ff000759f":"association learning","cnt_5024025b137a6":"","cnt_502403657d971":"reinstatement","cnt_50240446b8e2e":"association learning","cnt_50241122ad82b":"contingency learning","cnt_5024120d1b9af":"contingency learning","cnt_5024229cb9cef":"fear","cnt_502422c805b89":"anxiety","cnt_50295799192b3":"attention","cnt_50295a3179605":"attention","cnt_50295d51eda87":"attention","cnt_502a9a529d5d1":"figure ground segregation","cnt_502ac610413b0":"multistable perception","cnt_502ac6291faaa":"multistable perception","cnt_502ac644ac8c8":"figure ground segregation","cnt_502ace1922626":"border ownership","cnt_502acf9fbd81c":"multistable perception","cnt_502ade3a6b4d4":"body orientation","cnt_502ade46b2038":"body orientation","cnt_502ade521b4bd":"body orientation","cnt_502ade6246b25":"body orientation","cnt_502ade7522e56":"body orientation","cnt_502bef633e582":"lateral masking","cnt_5032be8b13109":"spontaneous recovery","cnt_50b40c06406f1":"decision making","cnt_50b40c3aa95af":"risk seeking","cnt_50b42fb7d7c9d":"psychological refractory period","cnt_50b55e6945a0e":"attention capacity","cnt_50b6603a36ae2":"iconic memory","cnt_50b666dabe619":"prejudice","cnt_50b667617b8fb":"implicit knowledge","cnt_50eb0b3d09ef0":"audition","cnt_50eb0ec7d3a0e":"crystallized intelligence","cnt_50eb12958b083":"adaptive control","cnt_50eb14da0c5d3":"episodic memory","cnt_50eb17d3cde37":"working memory","cnt_50eb183de4efb":"semantic memory","cnt_50eb1b6d46337":"processing capacity","cnt_50eb3da904b79":"reading","cnt_50eb3dca702f2":"perceptual identification","cnt_50eb42b349127":"episodic memory","cnt_50eb4e0450867":"motor control","cnt_50eb53a183bb6":"Strength","cnt_50eb55fe03a71":"balance","cnt_50eb6892e9317":"Locomotion","cnt_50eb6bfb7e504":"motor control","cnt_50f377a5d345e":"audition","cnt_50f37b522549b":"taste aversion","cnt_50f37cfea325a":"visual acuity","cnt_50f37f45b00e2":"happiness","cnt_50f38168aba37":"vestibular control","cnt_50f381d2aab5a":"visual acuity","cnt_50f38423c93aa":"olfactory perception","cnt_50f3bc8c135bc":"mood","cnt_50f3c03878ce3":"life satisfaction","cnt_50f582e4f0a26":"phonological loop","cnt_50f5bff7748da":"meaning","cnt_50f72efe2012e":"motor control","cnt_50f7303ade3dd":"category learning","cnt_50f7346907d30":"spatial memory","cnt_50f73673c04d8":"emotion recognition","cnt_50f73de372e77":"decision making","cnt_50f7409730966":"verbal memory","cnt_50f741b1591cf":"language processing","cnt_50f8444dd50db":"attention shifting","cnt_50f84d060a842":"cognitive control","cnt_50f84d6fe2b09":"prospective planning","cnt_50f84ec36494c":"motor control","cnt_50f851f7a2cf5":"sustained attention","cnt_50f853460010d":"visual search","cnt_50f862a47dd49":"spatial working memory","cnt_50f864a19c88d":"spatial working memory","cnt_50f99541d75ac":"abstract knowledge","cnt_50f9992176d5c":"verbal memory","cnt_50f999352af03":"episodic memory","cnt_50f99e5dc7aff":"face recognition","cnt_50f9db0e69e86":"spatial working memory","cnt_50f9db1e70ebe":"spatial working memory","cnt_5106ec3ec9e23":"generic knowledge","cnt_5106ef685b53d":"phonological working memory","cnt_5106ef70e1f21":"working memory","cnt_5106ef8038cf0":"working memory","cnt_5106f430082a0":"verbal fluency","cnt_5106f549c82ae":"mathematical reasoning","cnt_510707278e097":"visual perception","cnt_515490d277b2e":"working memory","cnt_5154924daead4":"working memory","cnt_5175b81f53bf3":"decision certainty","cnt_5181f79e38fb2":"potential monetary reward","cnt_5181f83b8eaae":"visual letter recognition","cnt_5181f863d5591":"visual pseudoword recognition","cnt_51ec19c434db0":"social cognition","cnt_51ec19d22283e":"attention shifting","cnt_51ec19df23bcb":"attentional focusing","cnt_51ec19f5be290":"communication","cnt_51ec1a03c57f1":"imagination","cnt_520613b7ec09c":"communication","cnt_520613c2e388b":"imagination","cnt_520613ce52654":"social intelligence","cnt_5206140b96f95":"restricted behavior","cnt_5206bf3813b0d":"cognitive development","cnt_5208ff7d82bce":"social intelligence","cnt_5208ffc82d64b":"social cognition","cnt_5208fff0019d6":"restricted behavior","cnt_520900032796f":"communication","cnt_520900265b01d":"social motivation","cnt_52167f5cba608":"visual memory","cnt_52167f717dac6":"verbal memory","cnt_52167f804e5e1":"verbal memory","cnt_52167f957d6ea":"declarative memory","cnt_52167fa84c173":"attentional focusing","cnt_52167fb957a15":"learning","cnt_52167fc85b968":"recognition","cnt_52168231ae8b5":"visual memory","cnt_52168a770f5c0":"social intelligence","cnt_52168a8712870":"communication","cnt_52168a9794c01":"restricted behavior","cnt_523c7cdacdc20":"irritability","cnt_523c7cf0ea7b4":"lethargy","cnt_523c7d0de6735":"restricted behavior","cnt_523c7d1fc539f":"hyperactivity","cnt_523c7d2b82709":"Inappropriate speech","cnt_523ca9488df58":"externalizing","cnt_523ca992819fd":"internalizing","cnt_523df6dc5a14b":"attention","cnt_523df7075b68e":"impulsivity","cnt_523df7166b0aa":"conduct disorder","cnt_523df727b2b2d":"antisocial personality","cnt_523df733af85f":"anxiety","cnt_523df74587157":"defiance","cnt_523df759d51e4":"fear","cnt_523df778821d2":"obsession","cnt_523df7816b16b":"obsession","cnt_523df78aee64c":"fear","cnt_523df7c01a116":"social phobia","cnt_523df7d6697ef":"anxiety","cnt_523df7e0f0100":"antisocial personality","cnt_523df7fc9aa9f":"delusion","cnt_523df8243edb4":"sadness","cnt_523df847494a2":"sadness","cnt_523dfd6ddf9ef":"antisocial personality","cnt_523dfd7f816b6":"rigidity","cnt_523dfd9d6a5ba":"social intelligence","cnt_523e12859c3ce":"cognitive development","cnt_523f592b5aaf9":"visual perception","cnt_523f593964534":"motor control","cnt_523f5c34d27c1":"social motivation","cnt_523f5c5e490b9":"impulsivity","cnt_523f5c6c34adc":"agreeableness","cnt_523f5c876e89c":"intelligence","cnt_524055e0365e7":"social motivation","cnt_524055ec1c81d":"social intelligence","cnt_52405600433b6":"restricted behavior","cnt_5240560bb6b8c":"conversational skill","cnt_52405bbeec6bc":"anxiety","cnt_52405bc94d887":"offensive (proactive) aggression","cnt_52405bd546e33":"sadness","cnt_52405be30419a":"somatosensation","cnt_52405bf41b0f9":"empathy","cnt_52405bff90283":"psychosis","cnt_52405c0bec117":"paranoia","cnt_52405c167b088":"obsession","cnt_52405c29582fb":"fear","cnt_524b4a79a1a62":"sadness","cnt_524b4ad9275ba":"offensive (proactive) aggression","cnt_524b4aef50da4":"internalizing","cnt_524b4afe10a65":"externalizing","cnt_524b4b1c6dd43":"anxiety","cnt_524b4b83ab297":"social phobia","cnt_524b4b8f51cef":"delusion","cnt_524b4baf1f04d":"obsession","cnt_524b4bc9ee0a0":"fear","cnt_524b4d978c37c":"conduct disorder","cnt_524b4db24ad5e":"defiance","cnt_524b5702780ad":"attentional focusing","cnt_524b570288099":"intrinsic motivation","cnt_524b570288b15":"social motivation","cnt_524b575f2b696":"social motivation","cnt_524b5772e43a8":"joint attention","cnt_524b578b851f8":"mood","cnt_5255c9e5a349e":"language production","cnt_5255c9f1ebfda":"pragmatic knowledge","cnt_5255c9fbe77f0":"social intelligence","cnt_5255cb7b65a68":"conversational speech","cnt_5255cb8a5a7c9":"communication","cnt_5255cbcce4b86":"syntax","cnt_5255cbd7b880a":"semantic knowledge","cnt_5255cbe8f3d77":"central coherence","cnt_5255cbf47097d":"social motivation","cnt_5255cc169ffda":"social context","cnt_5255cc441ddfb":"restricted behavior","cnt_52583b494605a":"sleep","cnt_52583b62b9127":"appetite","cnt_52583ba6ea3bd":"sadness","cnt_52583bbbcfd9c":"attentional focusing","cnt_52583bc89a63b":"anhedonia","cnt_52583bd8020da":"guilt","cnt_52583beae7af6":"lethargy","cnt_52583c058bea0":"suicidal ideation","cnt_525c4abf79872":"social intelligence","cnt_525c4ccfd861d":"inattention","cnt_525c4cdf291ad":"hyperactivity","cnt_525c4d023f957":"cognitive control","cnt_525c4d10ef555":"offensive (proactive) aggression","cnt_525c4d2927062":"social motivation","cnt_525c572fd0e6b":"defiance","cnt_525c57664d7a7":"hyperactivity","cnt_525c5771523cb":"anxiety","cnt_525c577f94423":"perfectionism","cnt_525c578b8e221":"somatosensation","cnt_525c57bbddf7c":"emotional expression","cnt_525c57d12435a":"impulsivity","cnt_525c5bbee5aa5":"inattention","cnt_525d84d3df53b":"language acquisition","cnt_525d84fa886ed":"speech production","cnt_525d8540300d6":"auditory perception","cnt_525d8551c4a1a":"word repetition","cnt_525d859ac7a85":"eating","cnt_525d85fbf2cb1":"hyperactivity","cnt_525d86eb4aeaa":"sleep","cnt_525d8738330eb":"defiance","cnt_525d8758edffb":"sensory defensiveness","cnt_525d876e43942":"obsession","cnt_525d879a4aca1":"sensitivity to change","cnt_525d87b78dee5":"restricted behavior","cnt_525d87fb5b1f1":"attachment","cnt_525d882970b5d":"noise sensitivity","cnt_525d88753a6ed":"imagination","cnt_525d888c5c514":"language","cnt_526027fdc9141":"phonological working memory","cnt_526028bb8afc0":"phonological encoding","cnt_52602c88d74b0":"obsession","cnt_52602e7ab102f":"phonological retrieval","cnt_5262c996e744b":"verbal fluency","cnt_5262cba00d9d1":"reasoning","cnt_5262cba80a837":"memory","cnt_5262cbbf50dc7":"mental imagery","cnt_5262cbd26aa57":"memory storage","cnt_5262cbed815c6":"memory storage","cnt_5262cbfa2cbb6":"recognition","cnt_5262cc0801239":"recognition","cnt_5262cc12a3d87":"association learning","cnt_5262cc25f2467":"association learning","cnt_5262cc368f077":"spatial memory","cnt_5262cc597b2b1":"sustained attention","cnt_5262cc64bb978":"divided attention","cnt_5262cd27045a1":"mental rotation","cnt_5262d6e7255a4":"motor control","cnt_5262d6f024e7d":"visual perception","cnt_5262d6ff7da05":"motor control","cnt_5262d709f36dd":"language production","cnt_5262d714c6169":"language processing","cnt_5262d98b148af":"offensive (proactive) aggression","cnt_5262d994b86f1":"arousal","cnt_5262d9a1aec5c":"phonological encoding","cnt_5262d9d19c56b":"fear","cnt_5262d9e96079d":"learning","cnt_5262d9fd26a5f":"restricted behavior","cnt_5262da1dbe022":"semantic knowledge","cnt_5262da3a15ba0":"social motivation","cnt_5266bcb8dd805":"language comprehension","cnt_5266bcd51c5bc":"communication","cnt_5266c222da58d":"word recognition","cnt_5266cc547e0dd":"language comprehension","cnt_5266cc7eb942a":"language production","cnt_526945035073c":"motor control","cnt_5269451644ae7":"noise sensitivity","cnt_52694f2f10eef":"visual perception","cnt_52694f7753cc0":"vestibular control","cnt_52694fa003431":"multisensory integration","cnt_52696df47325c":"proprioception","cnt_526994fa6650a":"emotion regulation","cnt_5269951211abd":"visual awareness","cnt_52699525e50e4":"emotional expression","cnt_52700368df6d8":"reasoning","cnt_52700566e4732":"language comprehension","cnt_527007430497f":"pattern recognition","cnt_52700c2f1cfc3":"quantitative skill","cnt_5271387cc163d":"language comprehension","cnt_52713899ea192":"language production","cnt_52713b2a0d0e7":"language","cnt_52713da7a1f5d":"language production","cnt_52713ea34e4a3":"language","cnt_52717634eaa19":"language","cnt_52717bb0bb848":"language production","cnt_52717cd1461e2":"language comprehension","cnt_52717eeade9e5":"defiance","cnt_52717eff2a75d":"social intelligence","cnt_52717f1a9b5ee":"imagination","cnt_5271807c80df3":"motor control","cnt_5271808f8f605":"motor control","cnt_5271869901fb5":"gaze","cnt_527186cd116f2":"communication","cnt_527186d95c3cb":"self control","cnt_527187cbb684e":"social intelligence","cnt_5271886ab5997":"joint attention","cnt_52718a35e6077":"theory of mind","cnt_52718a55b30db":"social cognition","cnt_52718a781a09a":"speech production","cnt_527280fcbc7f6":"naming","cnt_52728113402ad":"pattern recognition","cnt_52728125ee3cf":"phonological encoding","cnt_5272813e7ad58":"perceptual similarity","cnt_52728153ba9d7":"naming","cnt_52728198e8de8":"recall","cnt_527281ac7d9b4":"recall","cnt_527281ba2970c":"recall","cnt_527281e1d41da":"recall","cnt_52728205170c9":"quantitative skill","cnt_52728216c4a99":"perceptual similarity","cnt_52728224d01c3":"processing capacity","cnt_5272823262ea5":"language comprehension","cnt_5272823f1ac11":"word recognition","cnt_5297c9a46ea03":"defiance","cnt_5297c9dbcc0ef":"perfectionism","cnt_5297ca1f4b4b9":"social cognition","cnt_5298e7d15982e":"hyperactivity","cnt_5298e7de72d54":"attentional focusing","cnt_5298e7e9cce5d":"attention shifting","cnt_5298e814e6fcd":"fear","cnt_5298e8212f015":"frustration","cnt_5298e85d6d494":"impulsivity","cnt_5298e86a0ad46":"inhibition","cnt_5298e898828cf":"restricted behavior","cnt_5298e8b54ac46":"anticipation","cnt_5298e8c899b82":"sadness","cnt_5298ea6de528f":"social motivation","cnt_5298ed32ea678":"communication","cnt_5298ed452d73c":"restricted behavior","cnt_5298ed53c8281":"emotion regulation","cnt_5298ed5f7af62":"social cognition","cnt_5298fa8955db0":"joint attention","cnt_52991172871a9":"motor control","cnt_529911e50beb7":"motor control","cnt_5299143fed521":"anxiety","cnt_529ce0ceec559":"social motivation","cnt_529ce116b5cff":"joint attention","cnt_529cfb9f8cce6":"spatial ability","cnt_529cfc5925318":"intelligence","cnt_529d0a711d43d":"loneliness","cnt_52b4cfac3a8ce":"arousal","cnt_52dfa1b677494":"attention shifting","cnt_5358ef9570ace":"conflict adaptation effect","cnt_5358f019cdf06":"response conflict","cnt_54f8cb27bce65":"response selection","cnt_54f8cbcb6fab6":"color recognition","cnt_55245849e85e0":"auditory perception","cnt_552459a006d45":"visual perception","cnt_5526f6aa83790":"attention","cnt_5531474e117df":"emotional face recognition","cnt_55314757a78a1":"visual form recognition","cnt_553147b362347":"visual form recognition","cnt_55314940f18c6":"animacy perception","cnt_553149868c670":"visual pattern recognition","cnt_553149979dc2e":"relational comparison","cnt_553149bc9f9d1":"relational comparison","cnt_55314a10d4412":"auditory arithmetic processing","cnt_55314a1a5514c":"story comprehension","cnt_55314aff55913":"response execution","cnt_55314b0643005":"updating","cnt_55314b12878f7":"updating","cnt_55314b1edb310":"updating","cnt_55314b2a72bee":"visual body recognition","cnt_55314b49e5c9d":"visual face recognition","cnt_55314b56bceed":"visual place recognition","cnt_55314b5e393d2":"visual tool recognition","cnt_55315226076d3":"response selection","cnt_55315270d1e14":"left toe response execution","cnt_55315278ea6cc":"left finger response execution","cnt_5531528173117":"right toe response execution","cnt_5531528989cc7":"right finger response execution","cnt_553152908ac51":"tongue response execution","cnt_553999f2c69ef":"proactive control","cnt_55399a008d960":"error detection","cnt_55399a202b4ff":"response selection","cnt_55399a3f5e512":"response selection","cnt_55399d6bcd8dc":"error detection","cnt_55399dc274d97":"visual word recognition","cnt_55399e161c884":"visual word recognition","cnt_55399e3b3d13e":"visual word recognition","cnt_55399e44106d4":"visual pattern recognition","cnt_55399e5388e65":"visual object recognition","cnt_55399e5ab094d":"string maintenance","cnt_55399f4618e42":"visual object detection","cnt_55399f7c60721":"visual object detection","cnt_55399f8675b23":"risk","cnt_55399f9ac9c55":"visual object detection","cnt_55399fa95aaee":"task difficulty","cnt_553a65b8b5a92":"visual word recognition","cnt_553a6640aa059":"novelty detection","cnt_553a68284e225":"visual form recognition","cnt_553a682f464e7":"visual form recognition","cnt_553a689b663ed":"theory of mind","cnt_553a694a86e65":"error detection","cnt_553a6e24c3c78":"response execution","cnt_553a6e52baf3b":"subjective value judgment","cnt_553a6e6f8336e":"negative emotion","cnt_553a6e7daf8e6":"visual place recognition","cnt_553a6e9a84bd2":"visual word recognition","cnt_553a6ed942692":"emotional suppression","cnt_553a6f9fc8748":"error detection","cnt_553a6fb033bb0":"response conflict","cnt_553a6fbcbd6e6":"visual color discrimination","cnt_553a73a084bdd":"visual object recognition","cnt_553a767c981c7":"auditory perception","cnt_553a7683a550a":"auditory tone discrimination","cnt_553a768dc270f":"oddball detection","cnt_553a7710d845a":"visual form discrimination","cnt_553a7740160a3":"oddball detection","cnt_553e7a5b2584d":"subjective food value","cnt_553e85d4af020":"auditory sentence recognition","cnt_553e85f11747b":"auditory sentence recognition","cnt_553e85fc78496":"visual sentence recognition","cnt_553e86042df77":"visual sentence recognition","cnt_553e860cb6e0a":"auditory word recognition","cnt_553e8616191c4":"visual word recognition","cnt_553e865074ad4":"visual sentence recognition","cnt_553e865d69738":"auditory sentence recognition","cnt_553e8672a9f1d":"visual pattern recognition","cnt_553eb5457e145":"response execution","cnt_553eb550dc520":"facial attractiveness recognition","cnt_553eb5644f96f":"facial trustworthiness recognition","cnt_553eb56aa25df":"facial happiness recognition","cnt_553ec692268ca":"encoding","cnt_553ec6a0a72d3":"association learning","cnt_553fc4f4362c1":"response bias","cnt_553fc50126261":"monetary reward prediction error","cnt_553fcacc72dd6":"theory of mind","cnt_55410975ce70b":"causal inference","cnt_5541098145b5a":"causal inference","cnt_55410992b9c4b":"causal inference","cnt_554109af50e85":"theory of mind","cnt_554109c5544c8":"theory of mind","cnt_5542665e734fe":"","cnt_5585c855ab224":"sleep","cnt_55a300d4a2e78":"attention","cnt_55a3010bbd12c":"attention","cnt_55a30151c0e78":"attention","cnt_55a3018591a8d":"visual perception","cnt_55a301cd38de4":"visual perception","cnt_55a301d6d57b9":"auditory perception","cnt_55a30247227e5":"visual perception","cnt_55a302526f444":"visual perception","cnt_55a3028a5477b":"visual perception","cnt_55a302cbb1f7c":"auditory perception","cnt_55a30313da429":"auditory perception","cnt_55a303261a647":"auditory perception","cnt_55a3034ca0943":"auditory perception","cnt_55a3036a4175b":"auditory perception","cnt_55a303c74baf9":"auditory perception","cnt_55a30418945f9":"active maintenance","cnt_55a304556bac7":"","cnt_55a30468444a6":"","cnt_55a304d1cfc84":"Limited Capacity","cnt_55a3056e571ca":"Limited Capacity","cnt_55a3069a3b9f9":"declarative memory","cnt_55a306a830bfc":"declarative memory","cnt_55a306f9b7178":"declarative memory","cnt_55a30725ee445":"declarative memory","cnt_55a3075967471":"language","cnt_55c68750052fa":"high energy density food recognition","cnt_55ef1305643e9":"visual number recognition","cnt_55ef43b5be6da":"visual object maintenance","cnt_55ef440b3f6f2":"high energy density food recognition","cnt_5679bec3715cd":"negative emotion","cnt_573609d150d95":"task set","cnt_573609e3a736d":"task set","cnt_579614f464f73":"forgetting","cnt_579615e961f37":"forgetting","cnt_5796442240254":"syntactic processing","cnt_57964433e0efb":"syntactic processing","cnt_57964ea91ff76":"naming","cnt_5798c78bcea27":"visual word recognition","cnt_5798cd3deaac0":"language comprehension","cnt_5798d115b13e3":"motor sequence learning","cnt_5798d2b73fb3b":"semantic memory","cnt_5798f639d1544":"intelligence","cnt_5798f8797e2d6":"reading"}